bcf_extras/__init__.py
bcf_extras/add_header_lines.py
bcf_extras/copy_compress_index.py
bcf_extras/entry.py
bcf_extras/exceptions.py
bcf_extras/filter_gff3.py
bcf_extras/parallel_mergestr.py
bcf_extras/reformat_vcf_contigs.py
bcf_extras-0.2.0.dist-info/LICENSE
bcf_extras-0.2.0.dist-info/METADATA
bcf_extras-0.2.0.dist-info/WHEEL
bcf_extras-0.2.0.dist-info/entry_points.txt
bcf_extras-0.2.0.dist-info/top_level.txt
bcf_extras-0.2.0.dist-info/RECORD
