Metadata-Version: 2.1
Name: bcf-extras
Version: 0.2.0
Summary: A set of variant file helper utilities built on top of bcftools and htslib.
Home-page: https://github.com/davidlougheed/bcf_extras
Author: David Lougheed
Author-email: david.lougheed@gmail.com
License: GPLv3
Platform: UNKNOWN
Classifier: Programming Language :: Python :: 3 :: Only
Classifier: License :: OSI Approved :: GNU General Public License v3 (GPLv3)
Classifier: Operating System :: POSIX
Requires-Python: ~=3.7
License-File: LICENSE
Provides-Extra: str
Requires-Dist: trtools ; extra == 'str'
